scaledown/__init__.py
scaledown/api.py
scaledown/categories/__init__.py
scaledown/categories/category.py
scaledown/categories/category_manager.py
scaledown/cli/_init.py
scaledown/cli/commands.py
scaledown/models/__init__.py
scaledown/models/base_model.py
scaledown/models/claude_model.py
scaledown/models/llm_model.py
scaledown/models/model_factory.py
scaledown/models/model_registry.py
scaledown/models/openai_model.py
scaledown/optimization/__init__.py
scaledown/optimization/optimizer.py
scaledown/optimization/prompt_optimizers.py
scaledown/optimization/semantic_optimizer.py
scaledown/optimization/token_optimizer.py
scaledown/styles/__init__.py
scaledown/styles/default_styles.py
scaledown/styles/optimization_style.py
scaledown/styles/style.py
scaledown/styles/style_manager.py
scaledown/templates/__init__.py
scaledown/templates/default_templates.py
scaledown/templates/template.py
scaledown/templates/template_manager.py
scaledown/templates/template_registry.py
scaledown/tools/__init__.py
scaledown/tools/llms.py
scaledown/tools/prompt_optimizer.py
scaledown/tools/prompts.py
scaledown/utils/__init__.py
scaledown/utils/config.py
scaledown/utils/prompt_validator.py
scaledown/utils/token_counter.py
scaledown-0.1.4.dist-info/METADATA
scaledown-0.1.4.dist-info/WHEEL
scaledown-0.1.4.dist-info/entry_points.txt
scaledown-0.1.4.dist-info/RECORD
