Metadata-Version: 2.4
Name: scaledown
Version: 0.1.4
Summary: ScaleDown: A framework for LLM prompt optimization and model interaction
Project-URL: Homepage, https://github.com/your-username/modular-prompt-optimization
Project-URL: Repository, https://github.com/your-username/modular-prompt-optimization
Project-URL: Issues, https://github.com/your-username/modular-prompt-optimization/issues
Author-email: Your Name <your.email@example.com>
License: MIT
Keywords: ai,hallucination,llm,nlp,prompt-optimization
Classifier: Development Status :: 3 - Alpha
Classifier: Intended Audience :: Developers
Classifier: Intended Audience :: Science/Research
Classifier: License :: OSI Approved :: MIT License
Classifier: Programming Language :: Python :: 3
Classifier: Programming Language :: Python :: 3.9
Classifier: Programming Language :: Python :: 3.10
Classifier: Programming Language :: Python :: 3.11
Classifier: Topic :: Scientific/Engineering :: Artificial Intelligence
Requires-Python: >=3.9
Requires-Dist: accelerate
Requires-Dist: bitsandbytes; platform_system == 'Linux'
Requires-Dist: datasets
Requires-Dist: google-generativeai
Requires-Dist: huggingface-hub>=0.20.0
Requires-Dist: jsonlines
Requires-Dist: jupyter
Requires-Dist: langchain
Requires-Dist: langchain-community
Requires-Dist: langchain-openai
Requires-Dist: matplotlib
Requires-Dist: numpy
Requires-Dist: openai
Requires-Dist: pandas
Requires-Dist: python-dotenv
Requires-Dist: safetensors
Requires-Dist: seaborn
Requires-Dist: sparqlwrapper
Requires-Dist: torch>=2.0.1
Requires-Dist: transformers>=4.34.1
Requires-Dist: trl
Requires-Dist: wandb
Provides-Extra: dev
Requires-Dist: black>=23.0.0; extra == 'dev'
Requires-Dist: flake8>=6.0.0; extra == 'dev'
Requires-Dist: isort>=5.12.0; extra == 'dev'
Requires-Dist: pre-commit>=3.0.0; extra == 'dev'
Requires-Dist: pytest-cov>=4.0.0; extra == 'dev'
Requires-Dist: pytest>=7.0.0; extra == 'dev'
Provides-Extra: test
Requires-Dist: pytest-cov>=4.0.0; extra == 'test'
Requires-Dist: pytest>=7.0.0; extra == 'test'
